django_markdown_model/__init__.py
django_markdown_model/fields.py
django_markdown_model/models.py
django_markdown_model/utils/__init__.py
django_markdown_model/utils/constants.py
django_markdown_model-1.0.dist-info/LICENSE
django_markdown_model-1.0.dist-info/METADATA
django_markdown_model-1.0.dist-info/WHEEL
django_markdown_model-1.0.dist-info/top_level.txt
django_markdown_model-1.0.dist-info/RECORD
