Metadata-Version: 2.1
Name: django-markdown-model
Version: 1.0
Summary: This package allows you to store and render Markdown content effortlessly, making it ideal for applications that require rich text input from users.
Home-page: https://github.com/mohitprajapat2001/django-markdown-model
Author: Mohit Prajapat
Author-email: mohitdevelopment2001@gmail.com
Classifier: Framework :: Django
Classifier: Intended Audience :: Developers
Classifier: License :: OSI Approved :: MIT License
Classifier: Operating System :: OS Independent
Classifier: Programming Language :: Python :: 3
Classifier: Programming Language :: Python :: 3.8
Classifier: Programming Language :: Python :: 3.9
Classifier: Programming Language :: Python :: 3.10
Classifier: Programming Language :: Python :: 3.11
License-File: LICENSE
Requires-Dist: django>=5.1
